standup_notes/__init__.py
standup_notes/__main__.py
standup_notes/resources/__init__.py
standup_notes/resources/config.json
standup_notes/resources/standup-notes.bash
standup_notes/resources/standup.template
standup_notes-2.2.0.dist-info/LICENSE
standup_notes-2.2.0.dist-info/METADATA
standup_notes-2.2.0.dist-info/WHEEL
standup_notes-2.2.0.dist-info/entry_points.txt
standup_notes-2.2.0.dist-info/top_level.txt
standup_notes-2.2.0.dist-info/RECORD
