Metadata-Version: 2.1
Name: standup-notes
Version: 2.2.0
Summary: This is small tool for managing daily standup notes and getting them ready to be copy/pasted into another platform (i.e. virtual standup in Mattermost)
Home-page: http://www.mikemartino.ca
Author: Mike Martino
Author-email: mikemartino86@gmail.com
License: UNKNOWN
Platform: UNKNOWN
Classifier: Programming Language :: Python :: 3
Classifier: License :: OSI Approved :: MIT License
Classifier: Operating System :: OS Independent
Requires-Python: >=3.6
Requires-Dist: python-editor (==1.0.4)
Requires-Dist: pyperclip (==1.8.0)
Requires-Dist: pymsteams (==0.1.13)
